{
  "metadata": {
    "soundFile": "/Users/kavinduharshamal/Desktop/AIteaching-main/public/audio/LectureOne/2.wav",
    "duration": 1.2
  },
  "mouthCues": [
    { "start": 0.0, "end": 0.03, "value": "X" },
    { "start": 0.03, "end": 0.11, "value": "C" },
    { "start": 0.11, "end": 0.46, "value": "B" },
    { "start": 0.46, "end": 0.6, "value": "C" },
    { "start": 0.6, "end": 0.67, "value": "B" },
    { "start": 0.67, "end": 0.95, "value": "C" },
    { "start": 0.95, "end": 1.02, "value": "B" },
    { "start": 1.02, "end": 1.09, "value": "C" },
    { "start": 1.09, "end": 1.16, "value": "B" },
    { "start": 1.16, "end": 1.2, "value": "X" }
  ]
}
